[
	{ "type": "Physical Assets",  "item": "Commodity" },
	{ "type": "Physical Assets",  "item": "Real Estate" },
	{ "type": "Physical Assets",  "item": "Art" },
	{ "type": "Physical Assets",  "item": "Industrial Assets" },
	{ "type": "Physical Assets",  "item": "Collectibles" },
	{ "type": "Digital Assets",  "item": "Digital Art" },
	{ "type": "Digital Assets",  "item": "Digital Collectibles" },
	{ "type": "Digital Assets",  "item": "Music" },
	{ "type": "Digital Assets",  "item": "Gaming" },
	{ "type": "Digital Assets",  "item": "Corporate Branding" },
	{ "type": "Financial Assets",  "item": "Currencies" },
	{ "type": "Financial Assets",  "item": "Bonds" },
	{ "type": "Financial Assets",  "item": "Equities" },
	{ "type": "Financial Assets",  "item": "Investment Funds" },
	{ "type": "Financial Assets",  "item": "Loans" },
	{ "type": "Certifications",  "item": "Entry Tickets" },
	{ "type": "Certifications",  "item": "Proof of Participation" },
	{ "type": "Certifications",  "item": "Diplomas and Certificates" },
	{ "type": "Certifications",  "item": "Web Domains" },
	{ "type": "Certifications",  "item": "Proof of Maintenance" },
	{ "type": "Certifications",  "item": "Vouchers" },
	{ "type": "Certifications",  "item": "Loyalty Points" },
	{ "type": "Certifications",  "item": "Awards" }
]